XStatic_Font_Awesome-4.7.0.0-py2.7-nspkg.pth
XStatic_Font_Awesome-4.7.0.0.dist-info/DESCRIPTION.rst
XStatic_Font_Awesome-4.7.0.0.dist-info/METADATA
XStatic_Font_Awesome-4.7.0.0.dist-info/RECORD
XStatic_Font_Awesome-4.7.0.0.dist-info/WHEEL
XStatic_Font_Awesome-4.7.0.0.dist-info/metadata.json
XStatic_Font_Awesome-4.7.0.0.dist-info/namespace_packages.txt
XStatic_Font_Awesome-4.7.0.0.dist-info/top_level.txt
xstatic/pkg/font_awesome/__init__.py
xstatic/pkg/font_awesome/data/css/font-awesome.css
xstatic/pkg/font_awesome/data/css/font-awesome.min.css
xstatic/pkg/font_awesome/data/fonts/FontAwesome.otf
xstatic/pkg/font_awesome/data/fonts/fontawesome-webfont.eot
xstatic/pkg/font_awesome/data/fonts/fontawesome-webfont.svg
xstatic/pkg/font_awesome/data/fonts/fontawesome-webfont.ttf
xstatic/pkg/font_awesome/data/fonts/fontawesome-webfont.woff
xstatic/pkg/font_awesome/data/fonts/fontawesome-webfont.woff2
xstatic/pkg/font_awesome/data/less/animated.less
xstatic/pkg/font_awesome/data/less/bordered-pulled.less
xstatic/pkg/font_awesome/data/less/core.less
xstatic/pkg/font_awesome/data/less/fixed-width.less
xstatic/pkg/font_awesome/data/less/font-awesome.less
xstatic/pkg/font_awesome/data/less/icons.less
xstatic/pkg/font_awesome/data/less/larger.less
xstatic/pkg/font_awesome/data/less/list.less
xstatic/pkg/font_awesome/data/less/mixins.less
xstatic/pkg/font_awesome/data/less/path.less
xstatic/pkg/font_awesome/data/less/rotated-flipped.less
xstatic/pkg/font_awesome/data/less/screen-reader.less
xstatic/pkg/font_awesome/data/less/stacked.less
xstatic/pkg/font_awesome/data/less/variables.less
xstatic/pkg/font_awesome/data/scss/_animated.scss
xstatic/pkg/font_awesome/data/scss/_bordered-pulled.scss
xstatic/pkg/font_awesome/data/scss/_core.scss
xstatic/pkg/font_awesome/data/scss/_fixed-width.scss
xstatic/pkg/font_awesome/data/scss/_icons.scss
xstatic/pkg/font_awesome/data/scss/_larger.scss
xstatic/pkg/font_awesome/data/scss/_list.scss
xstatic/pkg/font_awesome/data/scss/_mixins.scss
xstatic/pkg/font_awesome/data/scss/_path.scss
xstatic/pkg/font_awesome/data/scss/_rotated-flipped.scss
xstatic/pkg/font_awesome/data/scss/_screen-reader.scss
xstatic/pkg/font_awesome/data/scss/_stacked.scss
xstatic/pkg/font_awesome/data/scss/_variables.scss
xstatic/pkg/font_awesome/data/scss/font-awesome.scss
