Metadata-Version: 2.0
Name: XStatic-Font-Awesome
Version: 4.7.0.0
Summary: Font-Awesome 4.7.0 (XStatic packaging standard)
Home-page: https://fortawesome.github.io/Font-Awesome/
Author: Rob Cresswell
Author-email: robert.cresswell@outlook.com
License: SIL OFL 1.1
Keywords: font_awesome xstatic
Platform: any
